{"PREVALENCE_BY_GENDER_AGE_YEAR":{"TRELLIS_NAME":["70-79","70-79","70-79","60-69","70-79","50-59","70-79","70-79","60-69"],"SERIES_NAME":["MALE","FEMALE","MALE","MALE","MALE","MALE","MALE","MALE","MALE"],"X_CALENDAR_YEAR":[2006,2007,2007,2007,2008,2008,2009,2010,2011],"Y_PREVALENCE_1000PP":[0.03624,0.03789,0.06661,0.02455,0.04278,0.0197,0.03161,0.03655,0.02184]},"PREVALENCE_BY_MONTH":{"X_CALENDAR_MONTH":[200703,200705,200706,200711,200804,200809,200902,201005,201010],"Y_PREVALENCE_1000PP":[0.00186,0.00123,0.00142,0.00137,0.00116,0.00209,0.00113,0.00133,0.00151]},"OBS_FREQUENCY_DISTRIBUTION":{"Y_NUM_PERSONS":[0,0,0,0,0],"X_COUNT":[1,2,3,4,5]},"OBSERVATIONS_BY_TYPE":{"CONCEPT_NAME":"Observation recorded from EHR","COUNT_VALUE":336},"AGE_AT_FIRST_OCCURRENCE":{"CATEGORY":["MALE","FEMALE"],"MIN_VALUE":[6,0],"P10_VALUE":[31,34],"P25_VALUE":[47,52],"MEDIAN_VALUE":[62,67],"P75_VALUE":[74,79],"P90_VALUE":[81,84],"MAX_VALUE":[95,96]}}
