{"PREVALENCE_BY_GENDER_AGE_YEAR":{"TRELLIS_NAME":"40-49","SERIES_NAME":"FEMALE","X_CALENDAR_YEAR":1997,"Y_PREVALENCE_1000PP":0.0914},"PREVALENCE_BY_MONTH":{"X_CALENDAR_MONTH":[199709,199711],"Y_PREVALENCE_1000PP":[0.00816,0.00785]},"OBS_FREQUENCY_DISTRIBUTION":{"Y_NUM_PERSONS":0,"X_COUNT":1},"OBSERVATIONS_BY_TYPE":{"CONCEPT_NAME":"Observation recorded from EHR","COUNT_VALUE":47},"AGE_AT_FIRST_OCCURRENCE":{"CATEGORY":["FEMALE","MALE"],"MIN_VALUE":[4,1],"P10_VALUE":[21,1],"P25_VALUE":[27,23],"MEDIAN_VALUE":[43,39],"P75_VALUE":[55,48],"P90_VALUE":[69,62],"MAX_VALUE":[77,62]}}
