{"PREVALENCE_BY_GENDER_AGE_YEAR":{"TRELLIS_NAME":[],"SERIES_NAME":[],"X_CALENDAR_YEAR":[],"Y_PREVALENCE_1000PP":[]},"PREVALENCE_BY_MONTH":{"X_CALENDAR_MONTH":[],"Y_PREVALENCE_1000PP":[]},"OBS_FREQUENCY_DISTRIBUTION":{"Y_NUM_PERSONS":[0,0],"X_COUNT":[1,2]},"OBSERVATIONS_BY_TYPE":{"CONCEPT_NAME":"Observation recorded from EHR","COUNT_VALUE":163},"AGE_AT_FIRST_OCCURRENCE":{"CATEGORY":["MALE","FEMALE"],"MIN_VALUE":[4,1],"P10_VALUE":[33,27],"P25_VALUE":[39,40],"MEDIAN_VALUE":[60,61],"P75_VALUE":[75,71],"P90_VALUE":[79,75],"MAX_VALUE":[100,91]}}
