{"PREVALENCE_BY_GENDER_AGE_YEAR":{"TRELLIS_NAME":["80-89","70-79","80-89","80-89","80-89"],"SERIES_NAME":["MALE","MALE","MALE","FEMALE","MALE"],"X_CALENDAR_YEAR":[2014,2016,2016,2016,2018],"Y_PREVALENCE_1000PP":[0.06344,0.03808,0.09527,0.09618,0.10085]},"PREVALENCE_BY_MONTH":{"X_CALENDAR_MONTH":[201508,201605,201606,201608,201809],"Y_PREVALENCE_1000PP":[0.00135,0.00177,0.00257,0.00214,0.00511]},"CONDITIONS_BY_TYPE":{"CONCEPT_NAME":"Observation recorded from EHR","COUNT_VALUE":129},"AGE_AT_FIRST_DIAGNOSIS":{"CATEGORY":["MALE","FEMALE"],"MIN_VALUE":[46,32],"P10_VALUE":[58,55],"P25_VALUE":[67,63],"MEDIAN_VALUE":[74,75],"P75_VALUE":[83,81],"P90_VALUE":[88,87],"MAX_VALUE":[97,90]}}
