{"PREVALENCE_BY_GENDER_AGE_YEAR":{"TRELLIS_NAME":["40-49","20-29"],"SERIES_NAME":["FEMALE","FEMALE"],"X_CALENDAR_YEAR":[2000,2011],"Y_PREVALENCE_1000PP":[0.03222,0.0173]},"PREVALENCE_BY_MONTH":{"X_CALENDAR_MONTH":200202,"Y_PREVALENCE_1000PP":0.00174},"CONDITIONS_BY_TYPE":{"CONCEPT_NAME":"Observation recorded from EHR","COUNT_VALUE":289},"AGE_AT_FIRST_DIAGNOSIS":{"CATEGORY":["MALE","FEMALE"],"MIN_VALUE":[2,8],"P10_VALUE":[17,17],"P25_VALUE":[23,21],"MEDIAN_VALUE":[31,33],"P75_VALUE":[44,48],"P90_VALUE":[69,62],"MAX_VALUE":[81,92]}}
