{"PREVALENCE_BY_GENDER_AGE_YEAR":{"TRELLIS_NAME":[],"SERIES_NAME":[],"X_CALENDAR_YEAR":[],"Y_PREVALENCE_1000PP":[]},"PREVALENCE_BY_MONTH":{"X_CALENDAR_MONTH":[201004,201005,201006,201008,201009,201010,201011,201106],"Y_PREVALENCE_1000PP":[0.00779,0.00781,0.0067,0.00784,0.00674,0.00675,0.01014,0.00686]},"CONDITIONS_BY_TYPE":{"CONCEPT_NAME":"EHR","COUNT_VALUE":170},"AGE_AT_FIRST_DIAGNOSIS":{"CATEGORY":[],"MIN_VALUE":[],"P10_VALUE":[],"P25_VALUE":[],"MEDIAN_VALUE":[],"P75_VALUE":[],"P90_VALUE":[],"MAX_VALUE":[]}}
