{"PREVALENCE_BY_GENDER_AGE_YEAR":{"TRELLIS_NAME":["30-39","30-39","30-39","30-39","30-39","30-39","30-39","30-39","30-39"],"SERIES_NAME":["FEMALE","FEMALE","FEMALE","FEMALE","FEMALE","FEMALE","FEMALE","FEMALE","FEMALE"],"X_CALENDAR_YEAR":[1999,2000,2002,2005,2006,2007,2010,2011,2013],"Y_PREVALENCE_1000PP":[0.0449,0.03521,0.01846,0.01624,0.0185,0.01773,0.01506,0.01487,0.01487]},"PREVALENCE_BY_MONTH":{"X_CALENDAR_MONTH":[],"Y_PREVALENCE_1000PP":[]},"PROCEDURE_FREQUENCY_DISTRIBUTION":{"Y_NUM_PERSONS":[0,0,0],"X_COUNT":[1,2,3]},"PROCEDURES_BY_TYPE":{"CONCEPT_NAME":"EHR order list entry","COUNT_VALUE":158},"AGE_AT_FIRST_OCCURRENCE":{"CATEGORY":"FEMALE","MIN_VALUE":23,"P10_VALUE":28,"P25_VALUE":31,"MEDIAN_VALUE":35,"P75_VALUE":38,"P90_VALUE":41,"MAX_VALUE":86}}
