{"PREVALENCE_BY_GENDER_AGE_YEAR":{"TRELLIS_NAME":["50-59","50-59","20-29","50-59","40-49","60-69","70-79"],"SERIES_NAME":["FEMALE","MALE","MALE","FEMALE","MALE","FEMALE","FEMALE"],"X_CALENDAR_YEAR":[2000,2005,2005,2007,2010,2011,2013],"Y_PREVALENCE_1000PP":[0.0402,0.01884,0.02266,0.01775,0.01332,0.02129,0.02623]},"PREVALENCE_BY_MONTH":{"X_CALENDAR_MONTH":[199910,200003,200112,200203,200407,200502,200505,200506,200710],"Y_PREVALENCE_1000PP":[0.00338,0.00397,0.00213,0.00172,0.00187,0.00136,0.00135,0.00134,0.00138]},"LENGTH_OF_ERA":{"CATEGORY":"Length of era","MIN_VALUE":1,"P10_VALUE":1,"P25_VALUE":1,"MEDIAN_VALUE":1,"P75_VALUE":1,"P90_VALUE":2,"MAX_VALUE":38},"AGE_AT_FIRST_DIAGNOSIS":{"CATEGORY":["MALE","FEMALE"],"MIN_VALUE":[2,0],"P10_VALUE":[21,25],"P25_VALUE":[40,41],"MEDIAN_VALUE":[55,56],"P75_VALUE":[67,68],"P90_VALUE":[77,78],"MAX_VALUE":[92,93]}}
