{"PREVALENCE_BY_GENDER_AGE_YEAR":{"TRELLIS_NAME":["80-89","80-89","80-89","80-89","70-79","80-89","70-79","80-89","70-79","80-89","80-89","80-89"],"SERIES_NAME":["FEMALE","FEMALE","MALE","FEMALE","FEMALE","FEMALE","FEMALE","FEMALE","FEMALE","FEMALE","FEMALE","FEMALE"],"X_CALENDAR_YEAR":[1999,2000,2001,2001,2002,2002,2003,2003,2004,2004,2005,2006],"Y_PREVALENCE_1000PP":[0.20757,0.14214,0.16016,0.11017,0.04963,0.14468,0.03569,0.10887,0.04394,0.10967,0.07285,0.05433]},"PREVALENCE_BY_MONTH":{"X_CALENDAR_MONTH":[200103,200209,200210,200303,200408],"Y_PREVALENCE_1000PP":[0.00211,0.00163,0.00376,0.00158,0.00139]},"CONDITIONS_BY_TYPE":{"CONCEPT_NAME":"Observation recorded from EHR","COUNT_VALUE":350},"AGE_AT_FIRST_DIAGNOSIS":{"CATEGORY":["FEMALE","MALE"],"MIN_VALUE":[63,57],"P10_VALUE":[74,71],"P25_VALUE":[79,78],"MEDIAN_VALUE":[83,82],"P75_VALUE":[88,87],"P90_VALUE":[92,90],"MAX_VALUE":[99,98]}}
