{"PREVALENCE_BY_GENDER_AGE_YEAR":{"TRELLIS_NAME":[],"SERIES_NAME":[],"X_CALENDAR_YEAR":[],"Y_PREVALENCE_1000PP":[]},"PREVALENCE_BY_MONTH":{"X_CALENDAR_MONTH":[200611,200707,201005],"Y_PREVALENCE_1000PP":[0.00147,0.00141,0.00114]},"CONDITIONS_BY_TYPE":{"CONCEPT_NAME":"Observation recorded from EHR","COUNT_VALUE":266},"AGE_AT_FIRST_DIAGNOSIS":{"CATEGORY":["FEMALE","MALE"],"MIN_VALUE":[3,0],"P10_VALUE":[23,11],"P25_VALUE":[37,49],"MEDIAN_VALUE":[56,66],"P75_VALUE":[78,78],"P90_VALUE":[87,84],"MAX_VALUE":[93,94]}}
