{"PREVALENCE_BY_GENDER_AGE_YEAR":{"TRELLIS_NAME":[],"SERIES_NAME":[],"X_CALENDAR_YEAR":[],"Y_PREVALENCE_1000PP":[]},"PREVALENCE_BY_MONTH":{"X_CALENDAR_MONTH":[],"Y_PREVALENCE_1000PP":[]},"OBS_FREQUENCY_DISTRIBUTION":{"Y_NUM_PERSONS":0,"X_COUNT":1},"OBSERVATIONS_BY_TYPE":{"CONCEPT_NAME":"Observation recorded from EHR","COUNT_VALUE":33},"AGE_AT_FIRST_OCCURRENCE":{"CATEGORY":["FEMALE","MALE"],"MIN_VALUE":[16,2],"P10_VALUE":[18,7],"P25_VALUE":[21,9],"MEDIAN_VALUE":[35,26],"P75_VALUE":[48,51],"P90_VALUE":[67,68],"MAX_VALUE":[78,74]}}
